lug/__init__.py
lug/constants.py
lug/containers.py
lug/lug.py
lug/module_detection.py
lug/shell.py
lug-0.3.8.dist-info/WHEEL
lug-0.3.8.dist-info/METADATA
lug-0.3.8.dist-info/LICENSE
lug-0.3.8.dist-info/RECORD
