Metadata-Version: 2.1
Name: lug
Version: 0.3.8
Summary: Run Python functions locally or in the cloud.
Home-page: https://lug.dev
License: Apache-2.0
Author: Justin Herr
Author-email: justin@trytoolchest.com
Requires-Python: >=3.8,<3.12
Classifier: License :: OSI Approved :: Apache Software License
Classifier: Operating System :: OS Independent
Classifier: Programming Language :: Python :: 3
Classifier: Programming Language :: Python :: 3.8
Classifier: Programming Language :: Python :: 3.9
Classifier: Programming Language :: Python :: 3.10
Classifier: Programming Language :: Python :: 3.11
Classifier: Programming Language :: Python :: 3
Requires-Dist: cloudpickle (>=2.2.0,<3.0.0)
Requires-Dist: docker (>=6.0.0,<7.0.0)
Requires-Dist: importlib-metadata (==4.13)
Requires-Dist: toolchest-client (>=0.11.14,<0.12.0)
Project-URL: Bug Tracker, https://github.com/trytoolchest/lug/issues
